geotiff_crop_dataset/__init__.py
geotiff_crop_dataset/dataset_reader.py
geotiff_crop_dataset/dataset_writer.py
geotiff_crop_dataset-0.0.1rc10.dist-info/LICENSE
geotiff_crop_dataset-0.0.1rc10.dist-info/METADATA
geotiff_crop_dataset-0.0.1rc10.dist-info/WHEEL
geotiff_crop_dataset-0.0.1rc10.dist-info/top_level.txt
geotiff_crop_dataset-0.0.1rc10.dist-info/RECORD
